checarplaca/__init__.py
checarplaca-0.2.0.dist-info/METADATA
checarplaca-0.2.0.dist-info/WHEEL
checarplaca-0.2.0.dist-info/top_level.txt
checarplaca-0.2.0.dist-info/RECORD
