Metadata-Version: 2.4
Name: checarplaca
Version: 0.2.0
Summary: Consulta dados a partir da placa do veículo.
Author-email: Daniel <devbatista61@gmail.com>
License: MIT
Keywords: ipva,placa,veiculo,consulta,checar
Classifier: Programming Language :: Python :: 3
Classifier: License :: OSI Approved :: MIT License
Classifier: Operating System :: OS Independent
Requires-Python: >=3.7
Requires-Dist: requests
Requires-Dist: beautifulsoup4
